cli_config_validator.py
cli_config_validator-0.1.0.dist-info/LICENSE
cli_config_validator-0.1.0.dist-info/METADATA
cli_config_validator-0.1.0.dist-info/WHEEL
cli_config_validator-0.1.0.dist-info/RECORD
